[
 {
   "large-bey-image": "images/full/ux-01-full.png",
   "bey-id": "01",
   "bey-lock": "",
   "bey-name": "Dran Buster",
   "bey-assist": "",
   "bey-ratchet": "1-60",
   "bey-bit": "Accel",
   "bey-line": "UX",
   "series": ""
 },
 {
   "large-bey-image": "images/full/ux-02-full.png",
   "bey-id": "02",
   "bey-lock": "",
   "bey-name": "Hells Hammer",
   "bey-assist": "",
   "bey-ratchet": "3-70",
   "bey-bit": "Hexa",
   "bey-line": "UX",
   "series": ""
 },
 {
   "large-bey-image": "images/full/ux-03-full.png",
   "bey-id": "03",
   "bey-lock": "",
   "bey-name": "Wizard Rod",
   "bey-assist": "",
   "bey-ratchet": "5-70",
   "bey-bit": "Disk Ball",
   "bey-line": "UX",
   "series": ""
 },
 {
   "large-bey-image": "images/full/ux-04-01-full.png",
   "bey-id": "04",
   "bey-lock": "",
   "bey-name": "Dran Buster",
   "bey-assist": "",
   "bey-ratchet": "1-60",
   "bey-bit": "Accel",
   "bey-line": "UX",
   "series": ""
 },
 {
   "large-bey-image": "images/full/ux-04-02-full.png",
   "bey-id": "04",
   "bey-lock": "",
   "bey-name": "Wizard Rod",
   "bey-assist": "",
   "bey-ratchet": "5-70",
   "bey-bit": "Disk Ball",
   "bey-line": "UX",
   "series": ""
 },
 {
   "large-bey-image": "images/full/ux-05-01-full.png",
   "bey-id": "05 01",
   "bey-lock": "",
   "bey-name": "Shinobi Shadow",
   "bey-assist": "",
   "bey-ratchet": "1-80",
   "bey-bit": "Metal Needle",
   "bey-line": "UX",
   "series": ""
 },
 {
   "large-bey-image": "images/full/ux-05-02.png",
   "bey-id": "05 02",
   "bey-lock": "",
   "bey-name": "Shinobi Shadow",
   "bey-assist": "",
   "bey-ratchet": "9-60",
   "bey-bit": "Low Flat",
   "bey-line": "UX",
   "series": ""
 },
 {
   "large-bey-image": "images/full/ux-05-03.png",
   "bey-id": "05 03",
   "bey-lock": "",
   "bey-name": "Shinobi Shadow",
   "bey-assist": "",
   "bey-ratchet": "3-70",
   "bey-bit": "Gear Point",
   "bey-line": "UX",
   "series": ""
 },
 {
   "large-bey-image": "images/full/ux-06-full.png",
   "bey-id": "06",
   "bey-lock": "",
   "bey-name": "Leon Crest",
   "bey-assist": "",
   "bey-ratchet": "7-60",
   "bey-bit": "Gear Needle",
   "bey-line": "UX",
   "series": ""
 },
 {
   "large-bey-image": "images/full/ux-07-01-full.png",
   "bey-id": "07",
   "bey-lock": "",
   "bey-name": "Phoenix Rudder",
   "bey-assist": "",
   "bey-ratchet": "9-70",
   "bey-bit": "Glide",
   "bey-line": "UX",
   "series": ""
 },
 {
   "large-bey-image": "images/full/ux-07-02.png",
   "bey-id": "07",
   "bey-lock": "",
   "bey-name": "Sphinx Cowl",
   "bey-assist": "",
   "bey-ratchet": "1-80",
   "bey-bit": "Gear Flat",
   "bey-line": "BX",
   "series": "UX"
 },
 {
   "large-bey-image": "images/full/ux-07-03.png",
   "bey-id": "07",
   "bey-lock": "",
   "bey-name": "Wyvern Gale",
   "bey-assist": "",
   "bey-ratchet": "2-60",
   "bey-bit": "Spike",
   "bey-line": "BX",
   "series": "UX"
 },
 {
   "large-bey-image": "images/full/ux-08-full.png",
   "bey-id": "08",
   "bey-lock": "",
   "bey-name": "Silver Wolf",
   "bey-assist": "",
   "bey-ratchet": "3-80",
   "bey-bit": "Free Ball",
   "bey-line": "UX",
   "series": ""
 },
 {
   "large-bey-image": "images/full/ux-09-full.png",
   "bey-id": "09",
   "bey-lock": "",
   "bey-name": "Samurai Saber",
   "bey-assist": "",
   "bey-ratchet": "2-70",
   "bey-bit": "Level",
   "bey-line": "UX",
   "series": ""
 },
 {
   "large-bey-image": "images/full/ux-10-01-full.png",
   "bey-id": "10",
   "bey-lock": "",
   "bey-name": "Knight Mail",
   "bey-assist": "",
   "bey-ratchet": "3-85",
   "bey-bit": "Bound Spike",
   "bey-line": "UX",
   "series": ""
 },
 {
   "large-bey-image": "images/full/ux-10-02.png",
   "bey-id": "10",
   "bey-lock": "",
   "bey-name": "Ptera Swing",
   "bey-assist": "",
   "bey-ratchet": "1-60",
   "bey-bit": "Ball",
   "bey-line": "BX",
   "series": "UX"
 },
 {
   "large-bey-image": "images/full/ux-10-03.png",
   "bey-id": "10",
   "bey-lock": "",
   "bey-name": "Tyranno Beat",
   "bey-assist": "",
   "bey-ratchet": "7-70",
   "bey-bit": "Rush",
   "bey-line": "BX",
   "series": "UX"
 },
 {
   "large-bey-image": "images/full/ux-10-04.png",
   "bey-id": "10",
   "bey-lock": "",
   "bey-name": "Hells Hammer",
   "bey-assist": "",
   "bey-ratchet": "1-60",
   "bey-bit": "Point",
   "bey-line": "UX",
   "series": ""
 },
 {
   "large-bey-image": "images/full/ux-11-full.png",
   "bey-id": "11",
   "bey-lock": "",
   "bey-name": "Impact Drake",
   "bey-assist": "",
   "bey-ratchet": "9-60",
   "bey-bit": "Low Rush",
   "bey-line": "UX",
   "series": ""
 },
 {
   "large-bey-image": "images/full/ux-12-01-full.png",
   "bey-id": "12 01",
   "bey-lock": "",
   "bey-name": "Ghost Circle",
   "bey-assist": "",
   "bey-ratchet": "0-80",
   "bey-bit": "Gear Ball",
   "bey-line": "UX",
   "series": ""
 },
 {
   "large-bey-image": "images/full/ux-12-02.png",
   "bey-id": "12 02",
   "bey-lock": "",
   "bey-name": "Ghost Circle",
   "bey-assist": "",
   "bey-ratchet": "4-60",
   "bey-bit": "Hexa",
   "bey-line": "UX",
   "series": ""
 },
 {
   "large-bey-image": "images/full/ux-12-03.png",
   "bey-id": "12 03",
   "bey-lock": "",
   "bey-name": "Shinobi Shadow",
   "bey-assist": "",
   "bey-ratchet": "3-80",
   "bey-bit": "Flat",
   "bey-line": "UX",
   "series": ""
 },
 {
   "large-bey-image": "images/full/ux-12-04.png",
   "bey-id": "12 04",
   "bey-lock": "",
   "bey-name": "Leon Claw",
   "bey-assist": "",
   "bey-ratchet": "0-80",
   "bey-bit": "Elevate",
   "bey-line": "BX",
   "series": "UX"
 },
 {
   "large-bey-image": "images/full/ux-12-05.png",
   "bey-id": "12 05",
   "bey-lock": "",
   "bey-name": "Phoenix Feather",
   "bey-assist": "",
   "bey-ratchet": "2-60",
   "bey-bit": "Needle",
   "bey-line": "BX",
   "series": "UX"
 },
 {
   "large-bey-image": "images/full/ux-12-06.png",
   "bey-id": "12 06",
   "bey-lock": "",
   "bey-name": "Wyvern Gale",
   "bey-assist": "",
   "bey-ratchet": "0-80",
   "bey-bit": "Cyclone",
   "bey-line": "BX",
   "series": "UX"
 },
 {
   "large-bey-image": "images/full/ux-13-full.png",
   "bey-id": "13",
   "bey-lock": "",
   "bey-name": "Golem Rock",
   "bey-assist": "",
   "bey-ratchet": "1-60",
   "bey-bit": "Under Needle",
   "bey-line": "UX",
   "series": ""
 },
 {
   "large-bey-image": "images/full/ux-14-full.png",
   "bey-id": "14",
   "bey-lock": "",
   "bey-name": "Scorpio Spear",
   "bey-assist": "",
   "bey-ratchet": "0-70",
   "bey-bit": "Zap",
   "bey-line": "UX",
   "series": ""
 },
 {
   "large-bey-image": "images/full/ux-15-01-full.png",
   "bey-id": "15",
   "bey-lock": "",
   "bey-name": "Shark Scale",
   "bey-assist": "",
   "bey-ratchet": "4-50",
   "bey-bit": "Under Flat",
   "bey-line": "UX",
   "series": ""
 },
 {
   "large-bey-image": "images/full/ux-15-02.png",
   "bey-id": "15",
   "bey-lock": "",
   "bey-name": "Tyranno Roar",
   "bey-assist": "",
   "bey-ratchet": "1-70",
   "bey-bit": "Level",
   "bey-line": "BX",
   "series": "UX"
 },
 {
   "large-bey-image": "images/full/ux-15-03.png",
   "bey-id": "15",
   "bey-lock": "Hells",
   "bey-name": "Brave",
   "bey-assist": "Jaggy",
   "bey-ratchet": "3-60",
   "bey-bit": "Gear Flat",
   "bey-line": "CX",
   "series": "UX"
 },
 {
   "large-bey-image": "images/full/ux-16-01-full.png",
   "bey-id": "16 01",
   "bey-lock": "",
   "bey-name": "Clock Mirage",
   "bey-assist": "",
   "bey-ratchet": "9-65",
   "bey-bit": "Ball",
   "bey-line": "UX",
   "series": ""
 },
 {
   "large-bey-image": "images/full/ux-16-02.png",
   "bey-id": "16 02",
   "bey-lock": "",
   "bey-name": "Clock Mirage",
   "bey-assist": "",
   "bey-ratchet": "9-65",
   "bey-bit": "Ball",
   "bey-line": "UX",
   "series": ""
 },
 {
   "large-bey-image": "images/full/ux-16-03.png",
   "bey-id": "16 03",
   "bey-lock": "",
   "bey-name": "Clock Mirage",
   "bey-assist": "",
   "bey-ratchet": "9-65",
   "bey-bit": "Ball",
   "bey-line": "UX",
   "series": ""
 },
 {
   "large-bey-image": "images/full/ux-17-full.png",
   "bey-id": "17",
   "bey-lock": "",
   "bey-name": "Meteor Dragoon",
   "bey-assist": "",
   "bey-ratchet": "3-70",
   "bey-bit": "Jolt",
   "bey-line": "UX",
   "series": ""
 },
 {
   "large-bey-image": "images/full/ux-18-01-full.png",
   "bey-id": "18 01",
   "bey-lock": "",
   "bey-name": "Mummy Curse",
   "bey-assist": "",
   "bey-ratchet": "7-55",
   "bey-bit": "Wedge",
   "bey-line": "UX",
   "series": ""
 },
 {
   "large-bey-image": "images/full/ux-18-02.png",
   "bey-id": "18 02",
   "bey-lock": "",
   "bey-name": "Mummy Curse",
   "bey-assist": "",
   "bey-ratchet": "4-60",
   "bey-bit": "Cyclone",
   "bey-line": "UX",
   "series": ""
 },
 {
   "large-bey-image": "images/full/ux-18-03.png",
   "bey-id": "18 03",
   "bey-lock": "Pegasus",
   "bey-name": "Brush",
   "bey-assist": "Massive",
   "bey-ratchet": "3-85",
   "bey-bit": "Wedge",
   "bey-line": "CX",
   "series": "UX"
 },
 {
   "large-bey-image": "images/full/ux-18-04.png",
   "bey-id": "18 04",
   "bey-lock": "Sol",
   "bey-name": "Brave",
   "bey-assist": "Charge",
   "bey-ratchet": "9-70",
   "bey-bit": "Trans Point",
   "bey-line": "CX",
   "series": "UX"
 },
 {
   "large-bey-image": "images/full/ux-18-05.png",
   "bey-id": "18 05",
   "bey-lock": "",
   "bey-name": "Dran Dagger",
   "bey-assist": "",
   "bey-ratchet": "7-55",
   "bey-bit": "Glide",
   "bey-line": "BX",
   "series": "UX"
 },
 {
   "large-bey-image": "images/full/ux-18-06.png",
   "bey-id": "18 06",
   "bey-lock": "",
   "bey-name": "Weiss Tiger",
   "bey-assist": "",
   "bey-ratchet": "4-80",
   "bey-bit": "Low Rush",
   "bey-line": "BX",
   "series": "UX"
 }
]